elevator_simulator/src/elevator.v
// 中文：電梯模組，實現樓層移動、門操作和請求處理
// English: Elevator module, implements floor movement, door operations, and request handling
module elevator #(
    parameter FLOOR_MIN = 1,       // 中文：最低樓層 | English: Minimum floor
    parameter FLOOR_MAX = 8,       // 中文：最高樓層 | English: Maximum floor
    parameter TIME_MOVE = 5,       // 中文：樓層移動時間 | English: Floor movement time
    parameter TIME_DOOR_OPEN = 5,  // 中文：開門時間 | English: Door open time
    parameter TIME_DOOR_HOLD = 5,  // 中文：開門保持時間 | English: Door hold time
    parameter TIME_DOOR_CLOSE = 5  // 中文：關門時間 | English: Door close time
) (
    input wire clk,                // 中文：時鐘信號 | English: Clock signal
    input wire rst,                // 中文：重置信號 | English: Reset signal
    input wire [FLOOR_MAX-1:0] internal_req, // 中文：內部樓層請求 | English: Internal floor requests
    input wire [FLOOR_MAX-1:0] external_up_req, // 中文：外部上行請求 | English: External up requests
    input wire [FLOOR_MAX-1:0] external_down_req, // 中文：外部下行請求 | English: External down requests
    output reg [3:0] current_floor, // 中文：當前樓層 | English: Current floor
    output reg door_state,         // 中文：門狀態（1=開，0=關） | English: Door state (1=open, 0=closed)
    output reg [1:0] elevator_state // 中文：電梯狀態（00=靜止，01=上行，10=下行） | English: Elevator state (00=idle, 01=up, 10=down)
);

// 中文：狀態定義，使用參數表示 FSM 狀態
// English: State definitions, using parameters for FSM states
parameter IDLE = 3'b000,          // 中文：靜止 | English: Idle
          MOVE_UP = 3'b001,       // 中文：上行 | English: Up
          MOVE_DOWN = 3'b010,     // 中文：下行 | English: Down
          DOOR_OPENING = 3'b011,  // 中文：開門 | English: Door opening
          DOOR_HOLD = 3'b100,     // 中文：保持開門 | English: Door hold
          DOOR_CLOSING = 3'b101;  // 中文：關門 | English: Door closing

reg [2:0] state, next_state;   // 中文：當前和下一個狀態 | English: Current and next state
reg [FLOOR_MAX-1:0] req_queue; // 中文：請求隊列 | English: Request queue
reg [3:0] target_floor;        // 中文：目標樓層 | English: Target floor
reg [3:0] timer;               // 中文：計時器 | English: Timer
reg timer_en;                  // 中文：計時器啟用 | English: Timer enable
reg direction;                 // 中文：方向（1=上行，0=下行） | English: Direction (1=up, 0=down)

// 中文：邊緣檢測，檢測輸入請求的上升沿
// English: Edge detection, detect rising edges of input requests
reg [FLOOR_MAX-1:0] prev_internal_req, prev_external_up_req, prev_external_down_req;
wire [FLOOR_MAX-1:0] new_internal_req, new_external_up_req, new_external_down_req;
assign new_internal_req = internal_req & ~prev_internal_req;
assign new_external_up_req = external_up_req & ~prev_external_up_req;
assign new_external_down_req = external_down_req & ~prev_external_down_req;

// 中文：初始化與重置，設置初始狀態和清零
// English: Initialization and reset, set initial state and clear signals
always @(posedge clk or posedge rst) begin
    if (rst) begin
        state <= IDLE;
        current_floor <= FLOOR_MIN;
        door_state <= 0;
        elevator_state <= 2'b00;
        req_queue <= 0;
        timer <= 0;
        direction <= 1; // 中文：預設上行 | English: Default to up
        prev_internal_req <= 0;
        prev_external_up_req <= 0;
        prev_external_down_req <= 0;
    end else begin
        state <= next_state;
        prev_internal_req <= internal_req;
        prev_external_up_req <= external_up_req;
        prev_external_down_req <= external_down_req;
        if (timer_en && timer > 0)
            timer <= timer - 1;
    end
end

// 中文：請求輸入處理，合併新請求到隊列
// English: Request input handling, merge new requests into queue
always @(posedge clk) begin
    if (rst)
        req_queue <= 0;
    else
        req_queue <= req_queue | new_internal_req | new_external_up_req | new_external_down_req;
end

// 中文：FSM 狀態轉換，控制電梯行為
// English: FSM state transitions, control elevator behavior
always @(*) begin
    next_state = state;
    timer_en = 0;
    case (state)
        IDLE: begin
            door_state = 0;
            elevator_state = 2'b00;
            if (req_queue != 0) begin
                target_floor = current_floor;
                next_state = IDLE;
                if (direction) begin
                    // 中文：上行掃描，選擇高於當前樓層的最高請求
                    // English: Upward scan, select highest request above current floor
                    begin : up_loop
                        integer i;
                        for (i = FLOOR_MAX-1; i >= FLOOR_MIN-1; i = i - 1) begin
                            if (req_queue[i] && (i+1 > current_floor)) begin
                                target_floor = i + 1;
                                next_state = MOVE_UP;
                                disable up_loop;
                            end
                        end
                    end
                end else begin
                    // 中文：下行掃描，選擇低於當前樓層的最高請求
                    // English: Downward scan, select highest request below current floor
                    begin : down_loop
                        integer i;
                        for (i = FLOOR_MAX-1; i >= FLOOR_MIN-1; i = i - 1) begin
                            if (req_queue[i] && (i+1 < current_floor)) begin
                                target_floor = i + 1;
                                next_state = MOVE_DOWN;
                                disable down_loop;
                            end
                        end
                    end
                end
            end
        end
        MOVE_UP: begin
            elevator_state = 2'b01;
            timer_en = 1;
            if (timer == 0) begin
                current_floor = current_floor + 1;
                if (current_floor == target_floor) begin
                    req_queue[target_floor-1] = 0;
                    next_state = DOOR_OPENING;
                    timer = TIME_DOOR_OPEN;
                end else begin
                    timer = TIME_MOVE;
                end
            end
        end
        MOVE_DOWN: begin
            elevator_state = 2'b10;
            timer_en = 1;
            if (timer == 0) begin
                current_floor = current_floor - 1;
                if (current_floor == target_floor) begin
                    req_queue[target_floor-1] = 0;
                    next_state = DOOR_OPENING;
                    timer = TIME_DOOR_OPEN;
                end else begin
                    timer = TIME_MOVE;
                end
            end
        end
        DOOR_OPENING: begin
            elevator_state = 2'b00;
            timer_en = 1;
            if (timer == 0) begin
                door_state = 1;
                next_state = DOOR_HOLD;
                timer = TIME_DOOR_HOLD;
            end
        end
        DOOR_HOLD: begin
            elevator_state = 2'b00;
            timer_en = 1;
            if (timer == 0) begin
                next_state = DOOR_CLOSING;
                timer = TIME_DOOR_CLOSE;
            end
        end
        DOOR_CLOSING: begin
            elevator_state = 2'b00;
            timer_en = 1;
            if (timer == 0) begin
                door_state = 0;
                next_state = IDLE;
                // 中文：檢查是否需要切換方向
                // English: Check if direction needs to be switched
                if (direction && (current_floor == FLOOR_MAX || !(req_queue & ((1 << (FLOOR_MAX-1)) - (1 << current_floor)))))
                    direction = 0;
                else if (!direction && (current_floor == FLOOR_MIN || !(req_queue & ((1 << (current_floor-1)) - 1))))
                    direction = 1;
            end
        end
        default: next_state = IDLE;
    endcase
end

endmodule

elevator_simulator/src/tb_elevator.v
// 電梯系統測試平台，模擬電梯的請求處理和狀態變化
// Elevator system testbench, simulates request handling and state transitions
module elevator_tb;
    // 參數定義，設置樓層範圍和時鐘週期
    // Parameter definitions for floor range and clock period
    parameter FLOOR_MIN = 1;        // 最低樓層 | Minimum floor
    parameter FLOOR_MAX = 8;        // 最高樓層 | Maximum floor
    parameter CLK_PERIOD = 10;      // 時鐘週期（單位時間） | Clock period (time units)

    // 信號宣告，定義輸入和輸出信號
    // Signal declarations for inputs and outputs
    reg clk, rst;                  // 時鐘和重置信號 | Clock and reset signals
    reg [FLOOR_MAX-1:0] internal_req, external_up_req, external_down_req; // 內部、外部上行和下行請求 | Internal, external up, and down requests
    wire [3:0] current_floor;      // 當前樓層 | Current floor
    wire door_state;               // 門狀態（1=開，0=關） | Door state (1=open, 0=closed)
    wire [1:0] elevator_state;     // 電梯狀態（00=靜止，01=上行，10=下行） | Elevator state (00=idle, 01=up, 10=down)

    // 實例化電梯模組，連接輸入和輸出
    // Instantiate the elevator module, connect inputs and outputs
    elevator #(
        .FLOOR_MIN(FLOOR_MIN),
        .FLOOR_MAX(FLOOR_MAX)
    ) uut (
        .clk(clk),
        .rst(rst),
        .internal_req(internal_req),
        .external_up_req(external_up_req),
        .external_down_req(external_down_req),
        .current_floor(current_floor),
        .door_state(door_state),
        .elevator_state(elevator_state)
    );

    // 時鐘生成，產生週期為 CLK_PERIOD 的時鐘信號
    // Clock generation, produces a clock signal with period CLK_PERIOD
    initial begin
        clk = 0;
        forever #(CLK_PERIOD/2) clk = ~clk;
    end

    // 狀態描述函數，將電梯狀態轉換為文字描述
    // State description function, converts elevator state to text
    function [31:0] elevator_state_desc;
        input [1:0] state;
        begin
            case (state)
                2'b00: elevator_state_desc = "Idle";    // 靜止 | Idle
                2'b01: elevator_state_desc = "Up";      // 上行 | Up
                2'b10: elevator_state_desc = "Down";    // 下行 | Down
                default: elevator_state_desc = "Unknown"; // 未知 | Unknown
            endcase
        end
    endfunction

    // 測試流程，模擬多種請求場景並輸出狀態
    // Test procedure, simulates various request scenarios and outputs states
    initial begin
        // 初始化，重置系統並清除所有請求
        // Initialization, reset the system and clear all requests
        rst = 1;
        internal_req = 0;
        external_up_req = 0;
        external_down_req = 0;
        #20 rst = 0;
        $display("Time=%0t: Reset completed", $time); // 重置完成 | Reset completed

        // 持續監控電梯狀態，顯示時間、樓層、門狀態等
        // Continuously monitor elevator state, display time, floor, door state, etc.
        $monitor("Time=%0t | Floor=%0d | Door=%s | State=%s | Target Floor=%0d | Req Queue=%b",
                 $time, current_floor, door_state ? "Open" : "Closed",
                 elevator_state_desc(elevator_state), uut.target_floor, uut.req_queue);

        // 測試案例 1 - 內部請求 4 樓，驗證基本移動
        // Test Case 1 - Internal request for floor 4, verify basic movement
        #10 internal_req[3] = 1; // 請求 4 樓 | Request floor 4
        $display("Time=%0t: Test Case 1 - Internal request for floor 4", $time);
        #100 internal_req[3] = 0;

        // 測試案例 2 - 外部上行請求 6 樓，內部請求 2 樓，測試相反方向請求
        // Test Case 2 - External up request for floor 6, internal request for floor 2, test opposite direction requests
        #50 external_up_req[5] = 1; // 請求 6 樓上行 | Request floor 6 up
        $display("Time=%0t: Test Case 2 - External up request for floor 6", $time);
        #10 internal_req[1] = 1;    // 請求 2 樓 | Request floor 2
        $display("Time=%0t: Test Case 2 - Internal request for floor 2", $time);
        #200 external_up_req[5] = 0;
        internal_req[1] = 0;

        // 測試案例 3 - 外部下行請求 3 樓，驗證下行處理
        // Test Case 3 - External down request for floor 3, verify downward movement
        #50 external_down_req[2] = 1; // 請求 3 樓下行 | Request floor 3 down
        $display("Time=%0t: Test Case 3 - External down request for floor 3", $time);
        #150 external_down_req[2] = 0;

        // 測試案例 4 - 多樓層連續內部請求（1 樓、5 樓、8 樓），驗證 FIFO 處理
        // Test Case 4 - Multiple internal requests (floors 1, 5, 8), verify FIFO handling
        #50 internal_req[0] = 1; // 請求 1 樓 | Request floor 1
        $display("Time=%0t: Test Case 4 - Internal request for floor 1", $time);
        #10 internal_req[4] = 1; // 請求 5 樓 | Request floor 5
        $display("Time=%0t: Test Case 4 - Internal request for floor 5", $time);
        #10 internal_req[7] = 1; // 請求 8 樓 | Request floor 8
        $display("Time=%0t: Test Case 4 - Internal request for floor 8", $time);
        #200 internal_req[0] = 0;
        internal_req[4] = 0;
        internal_req[7] = 0;

        // 測試案例 5 - 外部上行和下行請求同時發生（7 樓上行、3 樓下行），驗證方向優先
        // Test Case 5 - Simultaneous external up and down requests (floor 7 up, floor 3 down), verify direction priority
        #50 external_up_req[6] = 1; // 請求 7 樓上行 | Request floor 7 up
        external_down_req[2] = 1;   // 請求 3 樓下行 | Request floor 3 down
        $display("Time=%0t: Test Case 5 - External up request for floor 7, down request for floor 3", $time);
        #200 external_up_req[6] = 0;
        external_down_req[2] = 0;

        // 測試案例 6 - 邊界測試（1 樓外部下行、8 樓外部上行），驗證邊界行為
        // Test Case 6 - Boundary test (floor 1 down, floor 8 up), verify boundary behavior
        #50 external_down_req[0] = 1; // 請求 1 樓下行 | Request floor 1 down
        $display("Time=%0t: Test Case 6 - External down request for floor 1", $time);
        #10 external_up_req[7] = 1;   // 請求 8 樓上行 | Request floor 8 up
        $display("Time=%0t: Test Case 6 - External up request for floor 8", $time);
        #200 external_down_req[0] = 0;
        external_up_req[7] = 0;

        // 測試案例 7 - 快速連續請求（ 2 樓內部、4 樓上行、6 樓下行 ），驗證隊列更新
        // Test Case 7 - Rapid consecutive requests (floor 2 internal, floor 4 up, floor 6 down), verify queue updates
        #50 internal_req[1] = 1;      // 請求 2 樓 | Request floor 2
        $display("Time=%0t: Test Case 7 - Internal request for floor 2", $time);
        #10 external_up_req[3] = 1;   // 請求 4 樓上行 | Request floor 4 up
        $display("Time=%0t: Test Case 7 - External up request for floor 4", $time);
        #10 external_down_req[5] = 1; // 請求 6 樓下行 | Request floor 6 down
        $display("Time=%0t: Test Case 7 - External down request for floor 6", $time);
        #200 internal_req[1] = 0;
        external_up_req[3] = 0;
        external_down_req[5] = 0;

        // 結束模擬，輸出完成提示
        // End simulation, output completion message
        #200 $display("Time=%0t: Simulation finished", $time);
        $finish;
    end

    // 波形儲存，生成 VCD 檔案用於波形分析
    // Waveform storage, generate VCD file for waveform analysis
    initial begin
        $dumpfile("elevator.vcd");
        $dumpvars(0, elevator_tb);
    end
endmodule

elevator_simulator/src/elevator.vcd
$date
	Fri Jul 04 14:23:37 2025
$end
$version
	ModelSim Version 10.1d
$end
$timescale
	1ps
$end
$scope module elevator_tb $end
$var parameter 32 ! FLOOR_MIN $end
$var parameter 32 " FLOOR_MAX $end
$var parameter 32 # CLK_PERIOD $end
$var reg 1 $ clk $end
$var reg 1 % rst $end
$var reg 8 & internal_req [7:0] $end
$var reg 8 ' external_up_req [7:0] $end
$var reg 8 ( external_down_req [7:0] $end
$var wire 1 ) current_floor [3] $end
$var wire 1 * current_floor [2] $end
$var wire 1 + current_floor [1] $end
$var wire 1 , current_floor [0] $end
$var wire 1 - door_state $end
$var wire 1 . elevator_state [1] $end
$var wire 1 / elevator_state [0] $end
$scope function elevator_state_desc $end
$var reg 32 0 elevator_state_desc [31:0] $end
$var reg 2 1 state [1:0] $end
$upscope $end
$scope module uut $end
$var parameter 32 2 FLOOR_MIN $end
$var parameter 32 3 FLOOR_MAX $end
$var parameter 32 4 TIME_MOVE $end
$var parameter 32 5 TIME_DOOR_OPEN $end
$var parameter 32 6 TIME_DOOR_HOLD $end
$var parameter 32 7 TIME_DOOR_CLOSE $end
$var parameter 3 8 IDLE $end
$var parameter 3 9 MOVE_UP $end
$var parameter 3 : MOVE_DOWN $end
$var parameter 3 ; DOOR_OPENING $end
$var parameter 3 < DOOR_HOLD $end
$var parameter 3 = DOOR_CLOSING $end
$var wire 1 > clk $end
$var wire 1 ? rst $end
$var wire 1 @ internal_req [7] $end
$var wire 1 A internal_req [6] $end
$var wire 1 B internal_req [5] $end
$var wire 1 C internal_req [4] $end
$var wire 1 D internal_req [3] $end
$var wire 1 E internal_req [2] $end
$var wire 1 F internal_req [1] $end
$var wire 1 G internal_req [0] $end
$var wire 1 H external_up_req [7] $end
$var wire 1 I external_up_req [6] $end
$var wire 1 J external_up_req [5] $end
$var wire 1 K external_up_req [4] $end
$var wire 1 L external_up_req [3] $end
$var wire 1 M external_up_req [2] $end
$var wire 1 N external_up_req [1] $end
$var wire 1 O external_up_req [0] $end
$var wire 1 P external_down_req [7] $end
$var wire 1 Q external_down_req [6] $end
$var wire 1 R external_down_req [5] $end
$var wire 1 S external_down_req [4] $end
$var wire 1 T external_down_req [3] $end
$var wire 1 U external_down_req [2] $end
$var wire 1 V external_down_req [1] $end
$var wire 1 W external_down_req [0] $end
$var reg 4 X current_floor [3:0] $end
$var reg 1 Y door_state $end
$var reg 2 Z elevator_state [1:0] $end
$var reg 3 [ state [2:0] $end
$var reg 3 \ next_state [2:0] $end
$var reg 8 ] req_queue [7:0] $end
$var reg 4 ^ target_floor [3:0] $end
$var reg 4 _ timer [3:0] $end
$var reg 1 ` timer_en $end
$var reg 1 a direction $end
$var reg 8 b prev_internal_req [7:0] $end
$var reg 8 c prev_external_up_req [7:0] $end
$var reg 8 d prev_external_down_req [7:0] $end
$var wire 1 e new_internal_req [7] $end
$var wire 1 f new_internal_req [6] $end
$var wire 1 g new_internal_req [5] $end
$var wire 1 h new_internal_req [4] $end
$var wire 1 i new_internal_req [3] $end
$var wire 1 j new_internal_req [2] $end
$var wire 1 k new_internal_req [1] $end
$var wire 1 l new_internal_req [0] $end
$var wire 1 m new_external_up_req [7] $end
$var wire 1 n new_external_up_req [6] $end
$var wire 1 o new_external_up_req [5] $end
$var wire 1 p new_external_up_req [4] $end
$var wire 1 q new_external_up_req [3] $end
$var wire 1 r new_external_up_req [2] $end
$var wire 1 s new_external_up_req [1] $end
$var wire 1 t new_external_up_req [0] $end
$var wire 1 u new_external_down_req [7] $end
$var wire 1 v new_external_down_req [6] $end
$var wire 1 w new_external_down_req [5] $end
$var wire 1 x new_external_down_req [4] $end
$var wire 1 y new_external_down_req [3] $end
$var wire 1 z new_external_down_req [2] $end
$var wire 1 { new_external_down_req [1] $end
$var wire 1 | new_external_down_req [0] $end
$scope begin up_loop $end
$var integer 32 } i $end
$upscope $end
$scope begin down_loop $end
$var integer 32 ~ i $end
$upscope $end
$upscope $end
$upscope $end
$enddefinitions $end
#0
$dumpvars
0$
1%
b0 &
b0 '
b0 (
b1 X
0Y
b0 Z
b0 [
b0 \
b0 ]
bx ^
b0 _
0`
1a
b0 b
b0 c
b0 d
bx 0
bx 1
b1 !
b1000 "
b1010 #
b1 2
b1000 3
b101 4
b101 5
b101 6
b101 7
b0 8
b1 9
b10 :
b11 ;
b100 <
b101 =
bx }
bx ~
1,
0+
0*
0)
0-
0/
0.
0l
0k
0j
0i
0h
0g
0f
0e
0t
0s
0r
0q
0p
0o
0n
0m
0|
0{
0z
0y
0x
0w
0v
0u
0W
0V
0U
0T
0S
0R
0Q
0P
0O
0N
0M
0L
0K
0J
0I
0H
0G
0F
0E
0D
0C
0B
0A
0@
1?
0>
$end
#5
1$
1>
#10
0$
0>
#15
1$
1>
#20
0%
b0 1
b1001001011001000110110001100101 0
0$
0?
0>
#25
1$
1>
#30
b1000 &
0$
1D
1i
0>
#35
1$
1>
b1000 b
b1000 ]
0i
b1 ^
b111 }
b110 }
b101 }
b100 }
b11 }
b100 ^
b1 \
#40
0$
0>
#45
1$
1>
b1 [
b1 Z
1`
b10 X
b101 _
0,
1+
1/
b1 1
b101010101110000 0
#50
0$
0>
#55
1$
1>
b100 _
0`
1`
#60
0$
0>
#65
1$
1>
b11 _
0`
1`
#70
0$
0>
#75
1$
1>
b10 _
0`
1`
#80
0$
0>
#85
1$
1>
b1 _
0`
1`
#90
0$
0>
#95
1$
1>
b0 _
0`
1`
b11 X
b101 _
1,
#100
0$
0>
#105
1$
1>
b100 _
0`
1`
#110
0$
0>
#115
1$
1>
b11 _
0`
1`
#120
0$
0>
#125
1$
1>
b10 _
0`
1`
#130
b0 &
0$
0D
0>
#135
1$
1>
b0 b
b1 _
0`
1`
#140
0$
0>
#145
1$
1>
b0 _
0`
1`
b100 X
b0 ]
b11 \
b101 _
0,
0+
1*
#150
0$
0>
#155
1$
1>
b11 [
b100 _
0`
b0 Z
1`
0/
b0 1
b1001001011001000110110001100101 0
#160
0$
0>
#165
1$
1>
b11 _
0`
1`
#170
0$
0>
#175
1$
1>
b10 _
0`
1`
#180
b100000 '
0$
1J
1o
0>
#185
1$
1>
b100000 c
b1 _
b100000 ]
0o
0`
1`
#190
b10 &
0$
1F
1k
0>
#195
1$
1>
b10 b
b0 _
b100010 ]
0k
0`
1`
1Y
b100 \
b101 _
1-
#200
0$
0>
#205
1$
1>
b100 [
b100 _
0`
1`
#210
0$
0>
#215
1$
1>
b11 _
0`
1`
#220
0$
0>
#225
1$
1>
b10 _
0`
1`
#230
0$
0>
#235
1$
1>
b1 _
0`
1`
#240
0$
0>
#245
1$
1>
b0 _
0`
1`
b101 \
b101 _
#250
0$
0>
#255
1$
1>
b101 [
b100 _
0`
1`
#260
0$
0>
#265
1$
1>
b11 _
0`
1`
#270
0$
0>
#275
1$
1>
b10 _
0`
1`
#280
0$
0>
#285
1$
1>
b1 _
0`
1`
#290
0$
0>
#295
1$
1>
b0 _
0`
1`
0Y
b0 \
0-
#300
0$
0>
#305
1$
1>
b0 [
0`
b111 }
b110 }
b101 }
b110 ^
b1 \
#310
0$
0>
#315
1$
1>
b1 [
b1 Z
1`
b101 X
b101 _
1,
1/
b1 1
b101010101110000 0
#320
0$
0>
#325
1$
1>
b100 _
0`
1`
#330
0$
0>
#335
1$
1>
b11 _
0`
1`
#340
0$
0>
#345
1$
1>
b10 _
0`
1`
#350
0$
0>
#355
1$
1>
b1 _
0`
1`
#360
0$
0>
#365
1$
1>
b0 _
0`
1`
b110 X
b10 ]
b11 \
b101 _
0,
1+
#370
0$
0>
#375
1$
1>
b11 [
b100 _
0`
b0 Z
1`
0/
b0 1
b1001001011001000110110001100101 0
#380
0$
0>
#385
1$
1>
b11 _
0`
1`
#390
b0 '
b0 &
0$
0F
0J
0>
#395
1$
1>
b0 b
b0 c
b10 _
0`
1`
#400
0$
0>
#405
1$
1>
b1 _
0`
1`
#410
0$
0>
#415
1$
1>
b0 _
0`
1`
1Y
b100 \
b101 _
1-
#420
0$
0>
#425
1$
1>
b100 [
b100 _
0`
1`
#430
0$
0>
#435
1$
1>
b11 _
0`
1`
#440
b100 (
0$
1U
1z
0>
#445
1$
1>
b100 d
b10 _
b110 ]
0z
0`
1`
#450
0$
0>
#455
1$
1>
b1 _
0`
1`
#460
0$
0>
#465
1$
1>
b0 _
0`
1`
b101 \
b101 _
#470
0$
0>
#475
1$
1>
b101 [
b100 _
0`
1`
#480
0$
0>
#485
1$
1>
b11 _
0`
1`
#490
0$
0>
#495
1$
1>
b10 _
0`
1`
#500
0$
0>
#505
1$
1>
b1 _
0`
1`
#510
0$
0>
#515
1$
1>
b0 _
0`
1`
0Y
b0 \
0a
0-
#520
0$
0>
#525
1$
1>
b0 [
0`
b111 ~
b110 ~
b101 ~
b100 ~
b11 ~
b10 ~
b11 ^
b10 \
#530
0$
0>
#535
1$
1>
b10 [
b10 Z
1`
b101 X
b101 _
1,
0+
1.
b10 1
b1000100011011110111011101101110 0
#540
0$
0>
#545
1$
1>
b100 _
0`
1`
#550
0$
0>
#555
1$
1>
b11 _
0`
1`
#560
0$
0>
#565
1$
1>
b10 _
0`
1`
#570
0$
0>
#575
1$
1>
b1 _
0`
1`
#580
0$
0>
#585
1$
1>
b0 _
0`
1`
b100 X
b101 _
0,
#590
b0 (
0$
0U
0>
#595
1$
1>
b0 d
b100 _
0`
1`
#600
0$
0>
#605
1$
1>
b11 _
0`
1`
#610
0$
0>
#615
1$
1>
b10 _
0`
1`
#620
0$
0>
#625
1$
1>
b1 _
0`
1`
#630
0$
0>
#635
1$
1>
b0 _
0`
1`
b11 X
b10 ]
b11 \
b101 _
1,
1+
0*
#640
b1 &
0$
1G
1l
0>
#645
1$
1>
b11 [
b1 b
b100 _
b11 ]
0l
0`
b0 Z
1`
0.
b0 1
b1001001011001000110110001100101 0
#650
b10001 &
0$
1C
1h
0>
#655
1$
1>
b10001 b
b11 _
b10011 ]
0h
0`
1`
#660
b10010001 &
0$
1@
1e
0>
#665
1$
1>
b10010001 b
b10 _
b10010011 ]
0e
0`
1`
#670
0$
0>
#675
1$
1>
b1 _
0`
1`
#680
0$
0>
#685
1$
1>
b0 _
0`
1`
1Y
b100 \
b101 _
1-
#690
0$
0>
#695
1$
1>
b100 [
b100 _
0`
1`
#700
0$
0>
#705
1$
1>
b11 _
0`
1`
#710
0$
0>
#715
1$
1>
b10 _
0`
1`
#720
0$
0>
#725
1$
1>
b1 _
0`
1`
#730
0$
0>
#735
1$
1>
b0 _
0`
1`
b101 \
b101 _
#740
0$
0>
#745
1$
1>
b101 [
b100 _
0`
1`
#750
0$
0>
#755
1$
1>
b11 _
0`
1`
#760
0$
0>
#765
1$
1>
b10 _
0`
1`
#770
0$
0>
#775
1$
1>
b1 _
0`
1`
#780
0$
0>
#785
1$
1>
b0 _
0`
1`
0Y
b0 \
0-
#790
0$
0>
#795
1$
1>
b0 [
0`
b111 ~
b110 ~
b101 ~
b100 ~
b11 ~
b10 ~
b1 ~
b10 ^
b10 \
#800
0$
0>
#805
1$
1>
b10 [
b10 Z
1`
b10 X
b10010001 ]
b11 \
b101 _
0,
1.
b10 1
b1000100011011110111011101101110 0
#810
0$
0>
#815
1$
1>
b11 [
b100 _
0`
b0 Z
1`
0.
b0 1
b1001001011001000110110001100101 0
#820
0$
0>
#825
1$
1>
b11 _
0`
1`
#830
0$
0>
#835
1$
1>
b10 _
0`
1`
#840
0$
0>
#845
1$
1>
b1 _
0`
1`
#850
0$
0>
#855
1$
1>
b0 _
0`
1`
1Y
b100 \
b101 _
1-
#860
b10010000 &
b10000000 &
b0 &
0$
0G
0C
0@
0>
#865
1$
1>
b100 [
b0 b
b100 _
0`
1`
#870
0$
0>
#875
1$
1>
b11 _
0`
1`
#880
0$
0>
#885
1$
1>
b10 _
0`
1`
#890
0$
0>
#895
1$
1>
b1 _
0`
1`
#900
0$
0>
#905
1$
1>
b0 _
0`
1`
b101 \
b101 _
#910
b1000000 '
b100 (
0$
1U
1I
1n
1z
0>
#915
1$
1>
b101 [
b1000000 c
b100 d
b100 _
b11010101 ]
0z
0n
0`
1`
#920
0$
0>
#925
1$
1>
b11 _
0`
1`
#930
0$
0>
#935
1$
1>
b10 _
0`
1`
#940
0$
0>
#945
1$
1>
b1 _
0`
1`
#950
0$
0>
#955
1$
1>
b0 _
0`
1`
0Y
b0 \
0-
#960
0$
0>
#965
1$
1>
b0 [
0`
b111 ~
b110 ~
b101 ~
b100 ~
b11 ~
b10 ~
b1 ~
b0 ~
b1 ^
b10 \
#970
0$
0>
#975
1$
1>
b10 [
b10 Z
1`
b1 X
b11010100 ]
b11 \
b101 _
1,
0+
1.
b10 1
b1000100011011110111011101101110 0
#980
0$
0>
#985
1$
1>
b11 [
b100 _
0`
b0 Z
1`
0.
b0 1
b1001001011001000110110001100101 0
#990
0$
0>
#995
1$
1>
b11 _
0`
1`
#1000
0$
0>
#1005
1$
1>
b10 _
0`
1`
#1010
0$
0>
#1015
1$
1>
b1 _
0`
1`
#1020
0$
0>
#1025
1$
1>
b0 _
0`
1`
1Y
b100 \
b101 _
1-
#1030
0$
0>
#1035
1$
1>
b100 [
b100 _
0`
1`
#1040
0$
0>
#1045
1$
1>
b11 _
0`
1`
#1050
0$
0>
#1055
1$
1>
b10 _
0`
1`
#1060
0$
0>
#1065
1$
1>
b1 _
0`
1`
#1070
0$
0>
#1075
1$
1>
b0 _
0`
1`
b101 \
b101 _
#1080
0$
0>
#1085
1$
1>
b101 [
b100 _
0`
1`
#1090
0$
0>
#1095
1$
1>
b11 _
0`
1`
#1100
0$
0>
#1105
1$
1>
b10 _
0`
1`
#1110
b0 '
b0 (
0$
0U
0I
0>
#1115
1$
1>
b0 c
b0 d
b1 _
0`
1`
#1120
0$
0>
#1125
1$
1>
b0 _
0`
1`
0Y
b0 \
1a
0-
#1130
0$
0>
#1135
1$
1>
b0 [
0`
b111 }
b1000 ^
b1 \
#1140
0$
0>
#1145
1$
1>
b1 [
b1 Z
1`
b10 X
b101 _
0,
1+
1/
b1 1
b101010101110000 0
#1150
0$
0>
#1155
1$
1>
b100 _
0`
1`
#1160
b1 (
0$
1W
1|
0>
#1165
1$
1>
b1 d
b11 _
b11010101 ]
0|
0`
1`
#1170
b10000000 '
0$
1H
1m
0>
#1175
1$
1>
b10000000 c
b10 _
0m
0`
1`
#1180
0$
0>
#1185
1$
1>
b1 _
0`
1`
#1190
0$
0>
#1195
1$
1>
b0 _
0`
1`
b11 X
b101 _
1,
#1200
0$
0>
#1205
1$
1>
b100 _
0`
1`
#1210
0$
0>
#1215
1$
1>
b11 _
0`
1`
#1220
0$
0>
#1225
1$
1>
b10 _
0`
1`
#1230
0$
0>
#1235
1$
1>
b1 _
0`
1`
#1240
0$
0>
#1245
1$
1>
b0 _
0`
1`
b100 X
b101 _
0,
0+
1*
#1250
0$
0>
#1255
1$
1>
b100 _
0`
1`
#1260
0$
0>
#1265
1$
1>
b11 _
0`
1`
#1270
0$
0>
#1275
1$
1>
b10 _
0`
1`
#1280
0$
0>
#1285
1$
1>
b1 _
0`
1`
#1290
0$
0>
#1295
1$
1>
b0 _
0`
1`
b101 X
b101 _
1,
#1300
0$
0>
#1305
1$
1>
b100 _
0`
1`
#1310
0$
0>
#1315
1$
1>
b11 _
0`
1`
#1320
0$
0>
#1325
1$
1>
b10 _
0`
1`
#1330
0$
0>
#1335
1$
1>
b1 _
0`
1`
#1340
0$
0>
#1345
1$
1>
b0 _
0`
1`
b110 X
b101 _
0,
1+
#1350
0$
0>
#1355
1$
1>
b100 _
0`
1`
#1360
0$
0>
#1365
1$
1>
b11 _
0`
1`
#1370
b0 (
b0 '
0$
0H
0W
0>
#1375
1$
1>
b0 c
b0 d
b10 _
0`
1`
#1380
0$
0>
#1385
1$
1>
b1 _
0`
1`
#1390
0$
0>
#1395
1$
1>
b0 _
0`
1`
b111 X
b101 _
1,
#1400
0$
0>
#1405
1$
1>
b100 _
0`
1`
#1410
0$
0>
#1415
1$
1>
b11 _
0`
1`
#1420
b10 &
0$
1F
1k
0>
#1425
1$
1>
b10 b
b10 _
b11010111 ]
0k
0`
1`
#1430
b1000 '
0$
1L
1q
0>
#1435
1$
1>
b1000 c
b1 _
b11011111 ]
0q
0`
1`
#1440
b100000 (
0$
1R
1w
0>
#1445
1$
1>
b100000 d
b0 _
b11111111 ]
0w
0`
1`
b1000 X
b1111111 ]
b11 \
b101 _
0,
0+
0*
1)
#1450
0$
0>
#1455
1$
1>
b11 [
b100 _
0`
b0 Z
1`
0/
b0 1
b1001001011001000110110001100101 0
#1460
0$
0>
#1465
1$
1>
b11 _
0`
1`
#1470
0$
0>
#1475
1$
1>
b10 _
0`
1`
#1480
0$
0>
#1485
1$
1>
b1 _
0`
1`
#1490
0$
0>
#1495
1$
1>
b0 _
0`
1`
1Y
b100 \
b101 _
1-
#1500
0$
0>
#1505
1$
1>
b100 [
b100 _
0`
1`
#1510
0$
0>
#1515
1$
1>
b11 _
0`
1`
#1520
0$
0>
#1525
1$
1>
b10 _
0`
1`
#1530
0$
0>
#1535
1$
1>
b1 _
0`
1`
#1540
0$
0>
#1545
1$
1>
b0 _
0`
1`
b101 \
b101 _
